odoo/addons/l10n_ro_stock_account/README.rst
odoo/addons/l10n_ro_stock_account/__init__.py
odoo/addons/l10n_ro_stock_account/__manifest__.py
odoo/addons/l10n_ro_stock_account/i18n/l10n_ro_stock_account.pot
odoo/addons/l10n_ro_stock_account/i18n/ro.po
odoo/addons/l10n_ro_stock_account/models/__init__.py
odoo/addons/l10n_ro_stock_account/models/account_account.py
odoo/addons/l10n_ro_stock_account/models/account_invoice.py
odoo/addons/l10n_ro_stock_account/models/product.py
odoo/addons/l10n_ro_stock_account/models/res_company.py
odoo/addons/l10n_ro_stock_account/models/stock_location.py
odoo/addons/l10n_ro_stock_account/models/stock_move.py
odoo/addons/l10n_ro_stock_account/models/stock_picking.py
odoo/addons/l10n_ro_stock_account/models/stock_valuation_layer.py
odoo/addons/l10n_ro_stock_account/readme/CONTRIBUTORS.rst
odoo/addons/l10n_ro_stock_account/readme/DESCRIPTION.rst
odoo/addons/l10n_ro_stock_account/static/description/icon.png
odoo/addons/l10n_ro_stock_account/static/description/index.html
odoo/addons/l10n_ro_stock_account/tests/__init__.py
odoo/addons/l10n_ro_stock_account/tests/common.py
odoo/addons/l10n_ro_stock_account/tests/test_consum.py
odoo/addons/l10n_ro_stock_account/tests/test_inventory.py
odoo/addons/l10n_ro_stock_account/tests/test_product.py
odoo/addons/l10n_ro_stock_account/tests/test_purchase.py
odoo/addons/l10n_ro_stock_account/tests/test_retur.py
odoo/addons/l10n_ro_stock_account/tests/test_sale.py
odoo/addons/l10n_ro_stock_account/views/product_category_view.xml
odoo/addons/l10n_ro_stock_account/views/stock_location_view.xml
odoo/addons/l10n_ro_stock_account/views/stock_picking_view.xml
odoo/addons/l10n_ro_stock_account/views/stock_valuation_layer_views.xml
odoo/addons/l10n_ro_stock_account/wizard/__init__.py
odoo13_addon_l10n_ro_stock_account-13.0.1.2.0.dist-info/METADATA
odoo13_addon_l10n_ro_stock_account-13.0.1.2.0.dist-info/WHEEL
odoo13_addon_l10n_ro_stock_account-13.0.1.2.0.dist-info/top_level.txt
odoo13_addon_l10n_ro_stock_account-13.0.1.2.0.dist-info/RECORD
