Metadata-Version: 2.1
Name: odoo13-addon-l10n-ro-stock-account
Version: 13.0.1.2.0
Summary: Romania - Stock Accounting
Home-page: https://github.com/OCA/l10n-romania
Author: NextERP Romania,Dorin Hongu,Forest and Biomass Romania,Odoo Community Association (OCA)
Author-email: support@odoo-community.org
License: AGPL-3
Platform: UNKNOWN
Classifier: Programming Language :: Python
Classifier: Framework :: Odoo
Classifier: License :: OSI Approved :: GNU Affero General Public License v3
Requires-Python: >=3.5
Requires-Dist: odoo13-addon-l10n-ro-config
Requires-Dist: odoo13-addon-l10n-ro-stock
Requires-Dist: odoo (<13.1dev,>=13.0a)
